fmpstab/__init__.py
fmpstab/config_manager.py
fmpstab/dynamic.py
fmpstab/fmpstab_client.py
fmpstab/fmpstab_endpoints.json
fmpstab/fmpstab_websockets/__init__.py
fmpstab/fmpstab_websockets/base_websocket_client.py
fmpstab/fmpstab_websockets/crypto_websocket.py
fmpstab/fmpstab_websockets/forex_websocket.py
fmpstab/fmpstab_websockets/stock_websocket.py
fmpstab/logger.py
fmpstab/session.py
fmpstab-0.1.0.dist-info/WHEEL
fmpstab-0.1.0.dist-info/entry_points.txt
fmpstab-0.1.0.dist-info/METADATA
fmpstab-0.1.0.dist-info/RECORD
