Metadata-Version: 2.3
Name: fmpstab
Version: 0.1.0
Summary: A Stab at maintaining a Utility wrapper for the Financial Modeling Prep API. Uses the 'Stable' API. This is a cloned branch of fmp-stable-api
Requires-Dist: ratelimit>=2.2.1
Requires-Dist: requests>=2.32.5
Requires-Dist: websockets>=16.0
Requires-Python: >=3.14
